kw/json/__init__.py
kw/json/_compat.py
kw/json/encode.py
kw/json/exceptions.py
kw/json/flask.py
kw/json/utils.py
kiwi_json-0.10.1.dist-info/LICENSE
kiwi_json-0.10.1.dist-info/METADATA
kiwi_json-0.10.1.dist-info/WHEEL
kiwi_json-0.10.1.dist-info/top_level.txt
kiwi_json-0.10.1.dist-info/RECORD
