Metadata-Version: 2.1
Name: kiwi-json
Version: 0.10.1
Summary: DRY JSON encoder.
Home-page: https://github.com/kiwicom/kiwi-json
Author: Kiwi.com platform team
Author-email: platform@kiwi.com
Classifier: Development Status :: 4 - Beta
Classifier: Operating System :: OS Independent
Classifier: Programming Language :: Python :: 3.7
Classifier: Programming Language :: Python :: 3.8
Classifier: Programming Language :: Python :: 3.9
Classifier: Programming Language :: Python :: 3.10
License-File: LICENSE
